[
  {
    "id": 1,
    "title": "Electricity Bill - January 2025",
    "category": "Electricity",
    "units": 320,
    "rate": 7.5,
    "amount": 2400,
    "month": "January-2025",
    "status": "Paid",
    "date": "2025-01-31",
    "location": "Dhaka, Bangladesh",
    "image": "https://i.ibb.co/5gbsm5nG/sun-setting-silhouette-electricity-pylons.jpg",
    "description": "Monthly electricity bill covering 320 units consumed with a rate of 7.5 per unit for January 2025. Payment status: Paid."
  },
  {
    "id": 2,
    "title": "Water Bill - January 2025",
    "category": "Water",
    "units": 15,
    "rate": 30,
    "amount": 450,
    "month": "January-2025",
    "status": "Unpaid",
    "date": "2025-01-31",
    "location": "Dhaka, Bangladesh",
    "image": "https://i.ibb.co/Q7fs5Tjw/fresh-water-texture-background-transparent-liquid.jpg",
    "description": "Monthly water bill for 15 units consumed at a rate of 30 per unit for January 2025. Payment status: Unpaid."
  },
  {
    "id": 3,
    "title": "Gas Bill - January 2025",
    "category": "Gas",
    "units": 60,
    "rate": 18,
    "amount": 1080,
    "month": "January-2025",
    "status": "Paid",
    "date": "2025-01-31",
    "location": "Dhaka, Bangladesh",
    "image": "https://i.ibb.co/YFhxTjd7/modern-kitchen-stove-natural-gas-burns-with-blue-flame-household-gas-consumption-close-up-selective.jpg",
    "description": "Monthly gas bill for 60 units consumed at 18 per unit for January 2025. Payment status: Paid."
  },
  {
    "id": 4,
    "title": "Internet Bill - January 2025",
    "category": "Internet",
    "package": "40 Mbps",
    "amount": 1200,
    "month": "January-2025",
    "status": "Paid",
    "date": "2025-01-31",
    "location": "Dhaka, Bangladesh",
    "image": "https://example.com/images/internet.png",
    "description": "Internet service package 40 Mbps for January 2025. Total amount due is 1200. Payment status: Paid."
  },
  {
    "id": 5,
    "title": "Telephone Bill - January 2025",
    "category": "Telephone",
    "minutes_used": 300,
    "amount": 350,
    "month": "January-2025",
    "status": "Unpaid",
    "date": "2025-01-31",
    "location": "Dhaka, Bangladesh",
    "image": "https://i.ibb.co/dZ54pzq/close-up-person-working-call-center.jpg",
    "description": "Telephone bill for 300 minutes used in January 2025. Total amount due is 350. Payment status: Unpaid."
  },
  {
    "id": 6,
    "title": "House Rent - January 2025",
    "category": "House Rent",
    "amount": 9000,
    "month": "January-2025",
    "status": "Paid",
    "date": "2025-01-01",
    "location": "Dhaka, Bangladesh",
    "image": "https://i.ibb.co/ycLFHyKq/modern-luxury-home-with-beautiful-landscape.jpg",
    "description": "Monthly house rent for January 2025. Total amount is 9000. Payment status: Paid."
  },
  {
    "id": 7,
    "title": "Service Charge - January 2025",
    "category": "Service Charge",
    "amount": 1500,
    "month": "January-2025",
    "status": "Paid",
    "date": "2025-01-31",
    "location": "Dhaka, Bangladesh",
    "image": "https://i.ibb.co/Kj17Dx6r/customer-service-faqs-illustration.jpg",
    "description": "Service charge for common area maintenance and utilities for January 2025. Total amount: 1500. Status: Paid."
  },
  {
    "id": 8,
    "title": "Dust Cleaning - January 2025",
    "category": "Dust Cleaning",
    "amount": 200,
    "month": "January-2025",
    "status": "Paid",
    "date": "2025-01-31",
    "location": "Dhaka, Bangladesh",
    "image": "https://i.ibb.co/4R8DGNqq/medium-shot-woman-cleaning-home.jpg-",
    "description": "Monthly dust cleaning service for January 2025. Total cost: 200. Payment status: Paid."
  },
  {
    "id": 9,
    "title": "Security Guard Fee - January 2025",
    "category": "Security Guard Fee",
    "amount": 1200,
    "month": "January-2025",
    "status": "Unpaid",
    "date": "2025-01-31",
    "location": "Dhaka, Bangladesh",
    "image": "https://i.ibb.co/Q74CD179/portrait-male-security-guard-with-radio-station-camera-screens.jpg",
    "description": "Security guard service fee for January 2025. Total amount due: 1200. Payment status: Unpaid."
  },
  {
    "id": 10,
    "title": "Parking Fee - January 2025",
    "category": "Parking Fee",
    "amount": 800,
    "month": "January-2025",
    "status": "Paid",
    "date": "2025-01-31",
    "location": "Dhaka, Bangladesh",
    "image": "https://i.ibb.co/7xn6fNhK/empty-parking-lot-parking-lane-outdoor-public-park.jpg",
    "description": "Monthly parking fee for January 2025. Total amount: 800. Payment status: Paid."
  }
]
